CHANGES.txt
CREDITS.txt
LICENSE.txt
MANIFEST.in
README.rst
bootstrap.py
buildout.cfg
setup.py
tox.ini
more/__init__.py
more.forwarded.egg-info/PKG-INFO
more.forwarded.egg-info/SOURCES.txt
more.forwarded.egg-info/dependency_links.txt
more.forwarded.egg-info/namespace_packages.txt
more.forwarded.egg-info/not-zip-safe
more.forwarded.egg-info/requires.txt
more.forwarded.egg-info/top_level.txt
more/forwarded/__init__.py
more/forwarded/core.py
more/forwarded/forwarded.py
more/forwarded/tests/__init__.py
more/forwarded/tests/test_forwarded.py
more/forwarded/tests/test_tween.py