Metadata-Version: 1.0
Name: more.forwarded
Version: 0.1
Summary: Forwarded header support for Morepath
Home-page: http://pypi.python.org/pypi/more.static
Author: Martijn Faassen
Author-email: faassen@startifact.com
License: BSD
Keywords: morepath forwarded
Platform: UNKNOWN
